flask_easy/__init__.py
flask_easy/database.py
flask_easy/factory.py
flask_easy/instance.py
flask_easy/log.py
flask_easy/response.py
flask_easy/security.py
flask_easy/validator.py
flask_easy/exc/__init__.py
flask_easy/exc/app_exceptions.py
flask_easy/repository/__init__.py
flask_easy/repository/alchemy_sql_repository.py
flask_easy/repository/mongo.py
flask_easy/repository/repository_interface.py
flask_easy/repository/sql.py
flask_easy/scripts/__init__.py
flask_easy/scripts/cli.py
flask_easy/scripts/easy_scripts.py
flask_easy/scripts/resources/__init__.py
flask_easy/scripts/resources/model.py
flask_easy/scripts/resources/repository.py
flask_easy/scripts/resources/utils.py
flask_easy/scripts/resources/views.py
Flask_Easy-0.1.3.dist-info/LICENSE
Flask_Easy-0.1.3.dist-info/METADATA
Flask_Easy-0.1.3.dist-info/WHEEL
Flask_Easy-0.1.3.dist-info/entry_points.txt
Flask_Easy-0.1.3.dist-info/top_level.txt
Flask_Easy-0.1.3.dist-info/RECORD
