Metadata-Version: 2.1
Name: Flask-Easy
Version: 0.1.3
Author: Joseph Maclean Arhin
Author-email: me@josephmaclean.dev
License: BSD
Classifier: Environment :: Web Environment
Classifier: Intended Audience :: Developers
Classifier: License :: OSI Approved :: MIT License
Classifier: Operating System :: OS Independent
Classifier: Programming Language :: Python :: 3
Classifier: Topic :: Internet :: WWW/HTTP :: Dynamic Content
Classifier: Topic :: Internet :: WWW/HTTP :: WSGI
Classifier: Topic :: Internet :: WWW/HTTP :: WSGI :: Application
Classifier: Topic :: Software Development :: Libraries :: Application Frameworks
Requires-Python: >=3.8
License-File: LICENSE
Requires-Dist: Flask (>=2.1.3)
Requires-Dist: marshmallow (>=3.14.1)
Requires-Dist: blinker (>=1.4)
Requires-Dist: flasgger (>=0.9.5)
Requires-Dist: peewee (>=3.14.0)
Requires-Dist: peewee-migrate (>=1.4.8)
Requires-Dist: watchdog (>=2.1.2)
Requires-Dist: cookiecutter (>=1.7.3)
Requires-Dist: apispec (>=5.2.2)
Requires-Dist: faker (>=13.12.0)
